rac.py
setup.cfg
setup.py
bin/racadm
rac.egg-info/PKG-INFO
rac.egg-info/SOURCES.txt
rac.egg-info/dependency_links.txt
rac.egg-info/pbr.json
rac.egg-info/top_level.txt