Metadata-Version: 1.0
Name: rac
Version: 0.2
Summary: RAC module
Home-page: https://github.com/migrantgeek/python-rac
Author: Seth Miller
Author-email: seth@migrantgeek.com
License: UNKNOWN
Keywords: dell,rac,drac
Platform: UNKNOWN
